{
  "adan": "ille",
  "adang": "misit",
  "adeag": "debere",
  "adoug": "deos",
  "ag": "ante",
  "agand": "regum",
  "aglland": "legunt",
  "allo": "vos",
  "and": "nihil",
  "andad": "puto",
  "areat": "egit",
  "aw": "do",
  "bolleedag": "verbum",
  "cadog": "dico",
  "cag": "ego",
  "cead": "homo",
  "ceadag": "quidam",
  "ceado": "habuit",
  "ceag": "autem",
  "ceand": "nunc",
  "cecig": "possum",
  "cecond": "iterum",
  "cedag": "ut",
  "cedand": "amare",
  "cedog": "ipse",
  "ceeag": "ipsa",
  "ceedad": "sed",
  "ceedag": "trans",
  "ceedog": "capitis",
  "ceeg": "enim",
  "ceegag": "venit",
  "ceegam": "damus",
  "ceegand": "parvus",
  "ceego": "audio",
  "ceeo": "amo",
  "ceg": "in",
  "cegeand": "capere",
  "cegolland": "dominorum",
  "celleead": "quaedam",
  "ceo": "ex",
  "ceoceag": "magnae",
  "ceodand": "mittunt",
  "ceodkee": "legere",
  "ceodogr": "facere",
  "ceodoog": "dicere",
  "ceodos": "statim",
  "ceog": "et",
  "ceogad": "annos",
  "ceogadad": "hominum",
  "ceogam": "legit",
  "ceogand": "operum",
  "ceoged": "agunt",
  "ceogkeag": "dominos",
  "ceokeag": "secundum",
  "ceolg": "reges",
  "ceollag": "magnum",
  "ceolland": "sciendum",
  "ceollead": "forsitan",
  "ceolledag": "profecto",
  "ceolleead": "fortasse",
  "ceolleg": "post",
  "ceolog": "amant",
  "ceologledag": "quandoquidem",
  "ceoog": "res",
  "ceoollead": "temporis",
  "ceoollkag": "scribunt",
  "cloglo": "deorum",
  "collead": "numquam",
  "colleeag": "annorum",
  "colleed": "nominum",
  "cudag": "quam",
  "cuogad": "dedit",
  "dadadag": "manuum",
  "dag": "ad",
  "dand": "de",
  "daoag": "loca",
  "deag": "pars",
  "deaolledag": "praeter",
  "decdog": "sicut",
  "dedang": "nomen",
  "deeag": "dicunt",
  "deedag": "si",
  "deeead": "corpus",
  "deeedad": "diebus",
  "deog": "rei",
  "dllag": "debuit",
  "dodad": "eius",
  "dodag": "dant",
  "dodand": "huius",
  "dodaog": "generum",
  "doddollko": "protinus",
  "dodod": "illi",
  "dodor": "dies",
  "doead": "huic",
  "doeag": "inde",
  "doedag": "partis",
  "dog": "dat",
  "dogag": "iste",
  "doleeg": "nostri",
  "dolledag": "alterum",
  "dolleelle": "scribere",
  "dolog": "venit",
  "doogad": "debeo",
  "e": "sive",
  "g": "et",
  "gaeead": "fecit",
  "gag": "id",
  "ganig": "dico",
  "geag": "haec",
  "geceag": "tulit",
  "geceg": "amat",
  "gecod": "nomina",
  "gedear": "capit",
  "gedod": "habet",
  "gedog": "dicit",
  "geead": "habeo",
  "geeag": "ipsi",
  "geedad": "facit",
  "geedag": "mittit",
  "geeg": "opus",
  "geo": "tu",
  "geodand": "debent",
  "glledag": "scribo",
  "glledkea": "mittere",
  "go": "lex",
  "goakag": "mitto",
  "gocdog": "velle",
  "goceag": "ipsum",
  "gocedag": "partium",
  "gocgag": "dixit",
  "gockag": "ferre",
  "godag": "fero",
  "godang": "locus",
  "godead": "illum",
  "godeceag": "homines",
  "godog": "vel",
  "goedag": "inter",
  "goedand": "illius",
  "goedog": "vobis",
  "goeead": "legit",
  "goffedag": "civitas",
  "goflleeag": "causarum",
  "gog": "qui",
  "gogllog": "quidam",
  "gogod": "modus",
  "gogog": "tibi",
  "goleeag": "partes",
  "golfead": "generis",
  "golkag": "posse",
  "golkog": "locorum",
  "gollad": "quia",
  "golladag": "modo",
  "gollag": "sunt",
  "golland": "est",
  "gollao": "illo",
  "gollead": "nam",
  "golleag": "in",
  "golled": "causa",
  "golledag": "hoc",
  "golledog": "corporis",
  "golleead": "quattuor",
  "golleeag": "quod",
  "golleedag": "sub",
  "golleedo": "scribit",
  "golleedog": "quominus",
  "golleeeg": "dominus",
  "golleeg": "etiam",
  "golleg": "per",
  "gollekoag": "scripsit",
  "golleog": "habere",
  "gollkag": "putare",
  "gollkeda": "audiunt",
  "gollkeo": "volunt",
  "gollko": "agere",
  "gollkoag": "putavit",
  "gollkod": "factum",
  "gollkog": "putant",
  "gollleg": "potuit",
  "gollo": "ibi",
  "golload": "habent",
  "gollog": "esse",
  "golog": "genus",
  "goollead": "aliquid",
  "goolleeag": "temporum",
  "goolleeedag": "videatur",
  "gud": "ex",
  "gwrkag": "annus",
  "kag": "ago",
  "keadeag": "potest",
  "keag": "mei",
  "keakedag": "quinque",
  "keand": "ipsum",
  "kedag": "caput",
  "keead": "leges",
  "keedad": "capiunt",
  "keo": "me",
  "keodand": "magnus",
  "keoedag": "causae",
  "keog": "dei",
  "keogdag": "modorum",
  "kog": "hic",
  "lag": "anni",
  "llaad": "homo",
  "llag": "nos",
  "llandeg": "amavit",
  "llead": "venio",
  "lleadod": "causas",
  "lleador": "audire",
  "lledag": "domini",
  "lledand": "videre",
  "lleecollag": "civitatis",
  "lleed": "mihi",
  "lleedag": "voluit",
  "llkag": "volo",
  "lloc": "rex",
  "llodag": "omnis",
  "lloeag": "deum",
  "lloedag": "omnino",
  "lloeead": "istius",
  "llog": "deus",
  "llogag": "deitas",
  "llogog": "semper",
  "loeag": "bonus",
  "loedag": "nominis",
  "loeeo": "genera",
  "log": "dare",
  "o": "o",
  "oadad": "agit",
  "oband": "fert",
  "ocand": "loci",
  "oceag": "ens",
  "ocedag": "propter",
  "ocedog": "tempus",
  "oceead": "vestri",
  "oceeag": "istud",
  "odad": "tui",
  "odado": "diei",
  "odand": "legum",
  "odeeag": "illud",
  "odod": "opera",
  "oeokag": "cepit",
  "offedag": "super",
  "ofodag": "audit",
  "og": "non",
  "ogand": "vult",
  "ogeeg": "operis",
  "oglland": "venire",
  "oglleag": "capita",
  "ogllog": "ob",
  "okand": "regis",
  "okead": "manus",
  "okeead": "nobis",
  "okond": "legis",
  "ol": "ego",
  "oleado": "audivit",
  "olkog": "modi",
  "ollad": "aliud",
  "ollada": "illa",
  "ollag": "aut",
  "olland": "modos",
  "ollceg": "debet",
  "ollead": "cum",
  "olleag": "atque",
  "olled": "illi",
  "olledad": "adhuc",
  "olledag": "tamen",
  "olledang": "corpora",
  "olleeag": "nec",
  "olleeagand": "civitates",
  "olleeagdand": "civitatium",
  "olleed": "apud",
  "olleedag": "ab",
  "olleeedad": "adversus",
  "olleeg": "rebus",
  "olleeolland": "dicitur",
  "olleg": "video",
  "ollegag": "ferunt",
  "olleodag": "hominis",
  "olleodang": "corporum",
  "ollig": "facio",
  "ollkea": "vidit",
  "ollkeag": "vident",
  "ollked": "videt",
  "ollland": "umquam",
  "ollleag": "ergo",
  "ollledag": "aliquis",
  "ollleeedag": "propterea",
  "olload": "veniunt",
  "ollodeag": "possunt",
  "ollodog": "ipsius",
  "olloeag": "faciunt",
  "olloeg": "illam",
  "ollog": "pro",
  "ollogo": "putat",
  "ollooeodag": "faciunt",
  "ood": "his",
  "oxolleed": "quoddam",
  "vekeat": "contra"
}